aviationstack_mcp/__init__.py
aviationstack_mcp/__main__.py
aviationstack_mcp/server.py
aviationstack_mcp-1.3.1.dist-info/METADATA
aviationstack_mcp-1.3.1.dist-info/WHEEL
aviationstack_mcp-1.3.1.dist-info/entry_points.txt
aviationstack_mcp-1.3.1.dist-info/licenses/LICENSE
aviationstack_mcp-1.3.1.dist-info/RECORD
