Metadata-Version: 2.4
Name: aviationstack-mcp
Version: 1.3.1
Summary: An MCP server using the AviationStack API to fetch real-time flight data including airline flights, airport schedules, future flights and aircraft types
Project-URL: Homepage, https://github.com/pradumnasaraf/aviationstack-mcp
Project-URL: Repository, https://github.com/pradumnasaraf/aviationstack-mcp
Project-URL: Issues, https://github.com/pradumnasaraf/aviationstack-mcp/issues
Author-email: Pradumna Saraf <pradumnasaraf@gmail.com>
License-File: LICENSE
Keywords: ai,llm,mcp,model-context-protocol,server
Classifier: Intended Audience :: Developers
Classifier: License :: OSI Approved :: MIT License
Classifier: Operating System :: OS Independent
Classifier: Programming Language :: Python :: 3
Classifier: Programming Language :: Python :: 3 :: Only
Classifier: Programming Language :: Python :: 3.13
Classifier: Topic :: Scientific/Engineering :: Artificial Intelligence
Classifier: Topic :: Software Development :: Libraries :: Python Modules
Requires-Python: >=3.13
Requires-Dist: mcp[cli]>=1.10.1
Requires-Dist: requests
